weibo_scraper.py
weibo_base/__init__.py
weibo_base/weibo_api.py
weibo_base/weibo_util.py
weibo_scraper-1.0.6.dist-info/METADATA
weibo_scraper-1.0.6.dist-info/RECORD
weibo_scraper-1.0.6.dist-info/WHEEL
weibo_scraper-1.0.6.dist-info/top_level.txt
