Metadata-Version: 2.1
Name: weibo-scraper
Version: 1.0.6
Summary: UNKNOWN
Home-page: https://github.com/Xarrow/weibo-scraper
Author: helixcs
Author-email: zhangjian12424@gmail.com
License: MIT
Keywords: weibo scraper crawl
Platform: UNKNOWN
Classifier: License :: OSI Approved :: MIT License
Classifier: Programming Language :: Python
Classifier: Programming Language :: Python :: 3.6
Classifier: Programming Language :: Python :: Implementation :: CPython
Classifier: Programming Language :: Python :: Implementation :: PyPy
Requires-Python: >=3.6
Requires-Dist: requests
